evaluation/__init__.py
evaluation/eval_data_dump_read_speed_3d.py
evaluation/eval_data_dump_write_speed_3d.py
evaluation/eval_data_size_3d.py
evaluation/eval_nnunet_read_speed_2d.py
evaluation/eval_nnunet_read_speed_3d.py
evaluation/eval_random_dump_read_speed_3d.py
evaluation/eval_random_dump_write_speed_3d.py
evaluation/tmp.py
evaluation/tmp1.py
evaluation/utils.py
scarr/__init__.py
scarr/nifti2mzarr.py
scarr/scarr.py
scarr/tiff2mzarr.py
scarr/_tests/__init__.py
scifo/__init__.py
scifo/nifti2mzarr.py
scifo/scifo.py
scifo/tiff2mzarr.py
scifo/_tests/__init__.py
scifo-0.0.9.dist-info/LICENSE
scifo-0.0.9.dist-info/METADATA
scifo-0.0.9.dist-info/WHEEL
scifo-0.0.9.dist-info/top_level.txt
scifo-0.0.9.dist-info/RECORD
