Metadata-Version: 2.1
Name: scifo
Version: 0.0.9
Summary: Scifo (Scientific Zarr) is a Python library for working with the Scifo image format
Author: Karol Gotkowski
Author-email: karol.gotkowski@dkfz.de
License: Apache-2.0
Classifier: Development Status :: 2 - Pre-Alpha
Classifier: Intended Audience :: Developers
Classifier: License :: OSI Approved :: Apache Software License
Classifier: Operating System :: OS Independent
Classifier: Programming Language :: Python
Classifier: Programming Language :: Python :: 3
Classifier: Programming Language :: Python :: 3 :: Only
Classifier: Programming Language :: Python :: 3.8
Classifier: Programming Language :: Python :: 3.9
Classifier: Programming Language :: Python :: 3.10
Classifier: Topic :: Scientific/Engineering :: Image Processing
Requires-Python: >=3.8
License-File: LICENSE
Requires-Dist: numpy
Requires-Dist: scikit-image >=0.19
Requires-Dist: natsort
Requires-Dist: numcodecs
Requires-Dist: imagecodecs ==2023.1.23
Requires-Dist: zarr
Requires-Dist: tifffile
Provides-Extra: testing
Requires-Dist: tox ; extra == 'testing'
Requires-Dist: pytest ; extra == 'testing'
Requires-Dist: pytest-cov ; extra == 'testing'
